LICENSE
MANIFEST.in
README
setup.py
psycopg2ct/__init__.py
psycopg2ct/_config.py
psycopg2ct/compat.py
psycopg2ct/errorcodes.py
psycopg2ct/extensions.py
psycopg2ct/extras.py
psycopg2ct/pool.py
psycopg2ct/tz.py
psycopg2ct.egg-info/PKG-INFO
psycopg2ct.egg-info/SOURCES.txt
psycopg2ct.egg-info/dependency_links.txt
psycopg2ct.egg-info/top_level.txt
psycopg2ct/_impl/__init__.py
psycopg2ct/_impl/adapters.py
psycopg2ct/_impl/connection.py
psycopg2ct/_impl/consts.py
psycopg2ct/_impl/cursor.py
psycopg2ct/_impl/encodings.py
psycopg2ct/_impl/exceptions.py
psycopg2ct/_impl/libpq.py
psycopg2ct/_impl/lobject.py
psycopg2ct/_impl/notify.py
psycopg2ct/_impl/typecasts.py
psycopg2ct/_impl/util.py
psycopg2ct/_impl/xid.py
psycopg2ct/tests/__init__.py
psycopg2ct/tests/test_notify.py