Metadata-Version: 1.0
Name: psycopg2ct
Version: 2.4.4
Summary: An implementation of the psycopg2 module using ctypes.
Home-page: http://github.com/mvantellingen/psycopg2-ctypes
Author: Michael van Tellingen
Author-email: michaelvantellingen@gmail.com
License: LGPL
Platform: any
Classifier: Development Status :: 4 - Beta
Classifier: License :: OSI Approved :: GNU Library or Lesser General Public License (LGPL)
Classifier: Intended Audience :: Developers
Classifier: Programming Language :: Python :: 2.6
Classifier: Programming Language :: Python :: 2.7
Classifier: Programming Language :: Python :: Implementation :: CPython
Classifier: Programming Language :: Python :: Implementation :: PyPy
Classifier: Programming Language :: SQL
Classifier: Topic :: Database
Classifier: Topic :: Database :: Front-Ends
